OrcFxAPI.py
OrcFxAPIConfig.py
orcfxapi-11.6.1.dist-info/licenses/LICENCE
orcfxapi-11.6.1.dist-info/METADATA
orcfxapi-11.6.1.dist-info/WHEEL
orcfxapi-11.6.1.dist-info/top_level.txt
orcfxapi-11.6.1.dist-info/RECORD
