Metadata-Version: 2.4
Name: OrcFxAPI
Version: 11.6.1
Summary: Python interface to the OrcaFlex API
Author-email: Orcina <enquiry@orcina.com>
Project-URL: Homepage, https://www.orcina.com/
Classifier: Development Status :: 5 - Production/Stable
Classifier: Operating System :: Microsoft :: Windows
Classifier: Programming Language :: Python :: 3
Requires-Python: >=3.9
License-File: LICENCE
Requires-Dist: numpy>=1.19
Dynamic: license-file
